VoiceTrigger/__init__.py
VoiceTrigger/core/asmanager.py
VoiceTrigger/core/decorators.py
VoiceTrigger/core/speechr.py
VoiceTrigger/core/vldetector.py
VoiceTrigger/services/calibration.py
VoiceTrigger/utils/filter.py
VoiceTrigger/utils/levenshtein.py
VoiceTrigger/utils/logger.py
voicetrigger-1.0.4.dist-info/licenses/LICENSE
voicetrigger-1.0.4.dist-info/METADATA
voicetrigger-1.0.4.dist-info/WHEEL
voicetrigger-1.0.4.dist-info/top_level.txt
voicetrigger-1.0.4.dist-info/RECORD
