Metadata-Version: 2.4
Name: VoiceTrigger
Version: 1.0.4
Summary: Realtime-распознаватель речи на базе Vosk: управление микрофоном, детекция уровня голоса (whisper / normal / shout), опциональное шумоподавление, декораторный API для обработки текста, ключевых слов и быстрых команд.
Author-email: REYIL <azamatilbulov@gmail.com>
License: MIT
Classifier: Programming Language :: Python :: 3
Classifier: Programming Language :: Python :: 3.8
Classifier: Programming Language :: Python :: 3.9
Classifier: Programming Language :: Python :: 3.10
Classifier: Programming Language :: Python :: 3.11
Classifier: Programming Language :: Python :: 3.12
Classifier: License :: OSI Approved :: MIT License
Classifier: Operating System :: OS Independent
Requires-Python: <3.13,>=3.8
License-File: LICENSE
Requires-Dist: colorlog<7.0.0,>=6.10.1
Requires-Dist: noisereduce<4.0.0,>=3.0.0
Requires-Dist: numpy<2.0.0,>=1.22.0
Requires-Dist: scipy<2.0.0,>=1.10.0
Requires-Dist: sounddevice<0.6.0,>=0.4.4
Requires-Dist: vosk<0.4.0,>=0.3.45
Dynamic: license-file
